wt_mgr
