Metadata-Version: 1.0
Name: wt-mgr
Version: 0.1.7
Summary: Webex Teams Config Tool.
Home-page: UNKNOWN
Author: Federico Lovison
Author-email: flovison@cisco.com
License: UNKNOWN
Platform: UNKNOWN
